wireviz/DataClasses.py
wireviz/Harness.py
wireviz/__init__.py
wireviz/build_examples.py
wireviz/svgembed.py
wireviz/wireviz.py
wireviz/wv_bom.py
wireviz/wv_cli.py
wireviz/wv_colors.py
wireviz/wv_gv_html.py
wireviz/wv_helper.py
wireviz/wv_html.py
wireviz-0.4.dist-info/LICENSE
wireviz-0.4.dist-info/METADATA
wireviz-0.4.dist-info/WHEEL
wireviz-0.4.dist-info/entry_points.txt
wireviz-0.4.dist-info/top_level.txt
wireviz-0.4.dist-info/RECORD
