Metadata-Version: 2.1
Name: wireviz
Version: 0.4
Summary: Easily document cables and wiring harnesses
Home-page: https://github.com/formatc1702/WireViz
Author: Daniel Rojas
License: GPLv3
Keywords: cable connector hardware harness wiring wiring-diagram wiring-harness
Classifier: Development Status :: 4 - Beta
Classifier: Environment :: Console
Classifier: Programming Language :: Python :: 3
Classifier: Programming Language :: Python :: 3.7
Classifier: Programming Language :: Python :: 3.8
Classifier: Topic :: Utilities
Classifier: License :: OSI Approved :: GNU General Public License v3 (GPLv3)
License-File: LICENSE
Requires-Dist: click
Requires-Dist: pyyaml
Requires-Dist: pillow
Requires-Dist: graphviz
